config.py
mcp_core.py
overtime_task.py
jabanmcp-0.1.8.dist-info/METADATA
jabanmcp-0.1.8.dist-info/WHEEL
jabanmcp-0.1.8.dist-info/entry_points.txt
jabanmcp-0.1.8.dist-info/top_level.txt
jabanmcp-0.1.8.dist-info/RECORD
