Metadata-Version: 2.4
Name: jabanmcp
Version: 0.1.8
Summary: MCP tool for automatic overtime application based on daily reports
Requires-Python: >=3.10
Requires-Dist: requests
Requires-Dist: python-dotenv
